jupyter_anywidget_tesseract_pdfjs/__init__.py
jupyter_anywidget_tesseract_pdfjs/magics.py
jupyter_anywidget_tesseract_pdfjs/utils.py
jupyter_anywidget_tesseract_pdfjs/static/tesseract.css
jupyter_anywidget_tesseract_pdfjs/static/tesseract.js
jupyter_anywidget_tesseract_pdfjs/static/uuid.js
jupyter_anywidget_tesseract_pdfjs/static/widget.css
jupyter_anywidget_tesseract_pdfjs/static/widget.js
jupyter_anywidget_tesseract_pdfjs-0.0.8.dist-info/METADATA
jupyter_anywidget_tesseract_pdfjs-0.0.8.dist-info/WHEEL
jupyter_anywidget_tesseract_pdfjs-0.0.8.dist-info/licenses/LICENSE
jupyter_anywidget_tesseract_pdfjs-0.0.8.dist-info/RECORD
