Metadata-Version: 2.3
Name: jupyter_anywidget_tesseract_pdfjs
Version: 0.0.8
Project-URL: repository, https://github.com/innovationOUtside/jupyter_anywidget_tesseract_pdfjs
Author-email: Tony Hirst <tony.hirst@gmail.com>
License: Apache License
License-File: LICENSE
Requires-Dist: anywidget
Requires-Dist: puremagic
Provides-Extra: dev
Requires-Dist: jupyterlab; extra == 'dev'
Requires-Dist: watchfiles; extra == 'dev'
